AUTHORS
ChangeLog
LICENSE
README.md
requirements.txt
setup.cfg
setup.py
factclient/__init__.py
factclient/fact.py
factclient/testing.py
factclient/trace_pb2.py
factclient.egg-info/PKG-INFO
factclient.egg-info/SOURCES.txt
factclient.egg-info/dependency_links.txt
factclient.egg-info/not-zip-safe
factclient.egg-info/pbr.json
factclient.egg-info/requires.txt
factclient.egg-info/top_level.txt
factclient/io/ConsoleLogging.py
factclient/io/TCPSender.py
factclient/io/__init__.py
factclient/provider/AWSFact.py
factclient/provider/__init__.py